{
    "gaming": [
        {
            "six": [
                {
                    "price": 612.63,
                    "cpu": "Ryzen 5 5600",
                    "cooler": "Included with CPU",
                    "mobo": "ASRock B450M-HDV",
                    "ram": "G.Skill Ripjaws V 16GB",
                    "storage": "Patriot P300 512GB",
                    "gpu": "Intel Arc B580",
                    "case": "Phanteks XT Pro",
                    "psu": "EVGA 650BP"
                }
            ],
            "twelve": [
                {
                    "price": 1220.80,
                    "cpu": "Ryzen 5 7600X",
                    "cooler": "Thermalright Peerless Assassin 120",
                    "mobo": "MSI Pro B650-S",
                    "ram": "Corsair Vengeance 16GB",
                    "storage": "Crucial P3 Plus 2TB",
                    "gpu": "MSI Ventus RTX 4070",
                    "case": "NZXT H5 Flow",
                    "psu": "Corsair RM750e"
                }
            ],
            "twenty": [
                {
                    "price": 1993.90,
                    "cpu": "Ryzen 7 7800X3D",
                    "cooler": "Noctua NH-D15",
                    "mobo": "MSI MAG X670E Tomahawk",
                    "ram": "G.Skill Flare X5 32GB",
                    "storage": "Crucial P3 Plus 2TB",
                    "gpu": "ASRock Phantom RX 7900 XT",
                    "case": "Fractal Design Pop XL",
                    "psu": "Corsair RM850e"
                }
            ]
        }
    ],
    "rendering": [
        {
            "six": [
                {
                    "price": 612.63,
                    "cpu": "Ryzen 5 5600",
                    "cooler": "Included with CPU",
                    "mobo": "ASRock B450M-HDV",
                    "ram": "G.Skill Ripjaws V 16GB",
                    "storage": "Patriot P300 512GB",
                    "gpu": "Intel Arc B580",
                    "case": "Phanteks XT Pro",
                    "psu": "EVGA 650BP"
                }
            ],
            "twelve": [
                {
                    "price": 1177.21,
                    "cpu": "Ryzen 9 7900X",
                    "cooler": "Noctua NH-U12S",
                    "mobo": "MSI Pro B650-S",
                    "ram": "G.Skill Flare X5 32GB",
                    "storage": "Crucial P3 Plus 2TB",
                    "gpu": "Intel Arc B580",
                    "case": "NZXT H5 Flow",
                    "psu": "Corsair RM750e"
                }
            ],
            "twenty": [
                {
                    "price": 1990.84,
                    "cpu": "Ryzen 9 7950X",
                    "cooler": "Noctua NH-D15",
                    "mobo": "MSI MAG X670E Tomahawk",
                    "ram": "G.Skill Flare X5 64GB",
                    "storage": "2x Crucial P3 Plus 2TB",
                    "gpu": "Gigabyte Windforce RTX 4070 Super",
                    "case": "NZXT H5 Flow",
                    "psu": "Corsair RM750e"
                }
            ]
        }
    ],
    "development": [
        {
            "six": [
                {
                    "price": 612.84,
                    "cpu": "Ryzen 5 7600X",
                    "cooler": "Thermalright Peerless Assassin 120",
                    "mobo": "MSI Pro B650M-P",
                    "ram": "Corsair Vengeance 16GB",
                    "storage": "Crucial P3 Plus 1TB",
                    "gpu": "Onboard GPU",
                    "case": "Phanteks XT Pro",
                    "psu": "Corsair RM750e"
                }
            ],
            "twelve": [
                {
                    "price": 1199.23,
                    "cpu": "Ryzen 9 7900X",
                    "cooler": "Noctua NH-D15",
                    "mobo": "MSI Pro B650-S",
                    "ram": "G.Skill Flare X5 64GB",
                    "storage": "Samsung 990 Pro 2TB",
                    "gpu": "Onboard GPU",
                    "case": "Fractal Design North",
                    "psu": "Corsair RM850e"
                }
            ],
            "twenty": [
                {
                    "cpu": "Ryzen 9 9950X",
                    "cooler": "Noctua NH-D15",
                    "mobo": "ASRock X870 Pro RS",
                    "ram": "G.Skill Flare X5 64GB",
                    "gpu": "MSI Ventus RTX 4070",
                    "case": "Fractal Design North",
                    "psu": "Corsair RM850e"
                }
            ]
        }
    ]
}